<?xml version="1.0" encoding="UTF-8"?>
<objects serializationModel="Studio.02.02.00">
	<object class="AudioFile" id="{acaf7fcc-127f-4e46-8dc1-7cac52542e15}">
		<property name="assetPath">
			<value>525147__williamornelas__coins-selling-sound.wav</value>
		</property>
		<property name="frequencyInKHz">
			<value>44.0999985</value>
		</property>
		<property name="channelCount">
			<value>1</value>
		</property>
		<property name="length">
			<value>0.40498866213151929</value>
		</property>
		<relationship name="masterAssetFolder">
			<destination>{d39af037-a6ff-43a0-bfea-624040aa57b0}</destination>
		</relationship>
	</object>
</objects>
